tformat/__init__.py
tformat/tformat.py
tformat-0.1.0.dist-info/licenses/license.md
tformat-0.1.0.dist-info/METADATA
tformat-0.1.0.dist-info/WHEEL
tformat-0.1.0.dist-info/top_level.txt
tformat-0.1.0.dist-info/RECORD
