Metadata-Version: 2.4
Name: tformat
Version: 0.1.0
Summary: Efficient conversion of timestamps to human-readable equivalents
Home-page: https://github.com/cartertemm/tformat
Author: Carter Temm
Author-email: Carter Temm <cartertemm@gmail.com>
License-Expression: MIT OR CC0-1.0
Classifier: Programming Language :: Python :: 2
Classifier: Programming Language :: Python :: 3
Classifier: Operating System :: OS Independent
Classifier: Development Status :: 5 - Production/Stable
Classifier: Topic :: Utilities
Requires-Python: >=2
License-File: license.md
Dynamic: author
Dynamic: home-page
Dynamic: license-file
